setup.py
yfms/__init__.py
yfms.egg-info/PKG-INFO
yfms.egg-info/SOURCES.txt
yfms.egg-info/dependency_links.txt
yfms.egg-info/not-zip-safe
yfms.egg-info/top_level.txt