Metadata-Version: 1.0
Name: yfms
Version: 0.0.1
Summary: Financial Market Data
Home-page: http://github.com/byteatwork/yfms
Author: byteatwork
Author-email: byteatwork@gmail.com
License: MIT
Platform: UNKNOWN
